bbot/__init__.py
bbot/cli.py
bbot/core/__init__.py
bbot/core/config/__init__.py
bbot/core/config/files.py
bbot/core/config/logger.py
bbot/core/core.py
bbot/core/engine.py
bbot/core/event/__init__.py
bbot/core/event/base.py
bbot/core/event/helpers.py
bbot/core/flags.py
bbot/core/helpers/__init__.py
bbot/core/helpers/async_helpers.py
bbot/core/helpers/bloom.py
bbot/core/helpers/cache.py
bbot/core/helpers/command.py
bbot/core/helpers/depsinstaller/__init__.py
bbot/core/helpers/depsinstaller/installer.py
bbot/core/helpers/depsinstaller/sudo_askpass.py
bbot/core/helpers/diff.py
bbot/core/helpers/dns/__init__.py
bbot/core/helpers/dns/brute.py
bbot/core/helpers/dns/dns.py
bbot/core/helpers/dns/engine.py
bbot/core/helpers/dns/helpers.py
bbot/core/helpers/dns/mock.py
bbot/core/helpers/files.py
bbot/core/helpers/git.py
bbot/core/helpers/helper.py
bbot/core/helpers/interactsh.py
bbot/core/helpers/libmagic.py
bbot/core/helpers/misc.py
bbot/core/helpers/names_generator.py
bbot/core/helpers/ntlm.py
bbot/core/helpers/process.py
bbot/core/helpers/ratelimiter.py
bbot/core/helpers/regex.py
bbot/core/helpers/regexes.py
bbot/core/helpers/url.py
bbot/core/helpers/validators.py
bbot/core/helpers/web/__init__.py
bbot/core/helpers/web/client.py
bbot/core/helpers/web/engine.py
bbot/core/helpers/web/envelopes.py
bbot/core/helpers/web/ssl_context.py
bbot/core/helpers/web/web.py
bbot/core/helpers/wordcloud.py
bbot/core/helpers/yara_helper.py
bbot/core/modules.py
bbot/core/multiprocess.py
bbot/core/shared_deps.py
bbot/db/sql/models.py
bbot/defaults.yml
bbot/errors.py
bbot/logger.py
bbot/modules/__init__.py
bbot/modules/ajaxpro.py
bbot/modules/anubisdb.py
bbot/modules/apkpure.py
bbot/modules/aspnet_bin_exposure.py
bbot/modules/azure_realm.py
bbot/modules/azure_tenant.py
bbot/modules/baddns.py
bbot/modules/baddns_direct.py
bbot/modules/baddns_zone.py
bbot/modules/badsecrets.py
bbot/modules/base.py
bbot/modules/bevigil.py
bbot/modules/bucket_amazon.py
bbot/modules/bucket_digitalocean.py
bbot-2.8.1.dist-info/METADATA
bbot-2.8.1.dist-info/WHEEL
bbot-2.8.1.dist-info/entry_points.txt
bbot-2.8.1.dist-info/licenses/LICENSE
bbot-2.8.1.dist-info/RECORD
