Metadata-Version: 2.4
Name: bbot
Version: 2.8.1
Summary: OSINT automation for hackers.
License: GPL-3.0
License-File: LICENSE
Keywords: python,cli,automation,osint,threat-intel,intelligence,neo4j,scanner,python-library,hacking,recursion,pentesting,recon,command-line-tool,bugbounty,subdomains,security-tools,subdomain-scanner,osint-framework,attack-surface,subdomain-enumeration,osint-tool
Author: TheTechromancer
Requires-Python: >=3.9,<4.0
Classifier: License :: OSI Approved :: GNU General Public License v3 (GPLv3)
Classifier: Operating System :: POSIX :: Linux
Classifier: Programming Language :: Python :: 3
Classifier: Programming Language :: Python :: 3.9
Classifier: Programming Language :: Python :: 3.10
Classifier: Programming Language :: Python :: 3.11
Classifier: Programming Language :: Python :: 3.12
Classifier: Programming Language :: Python :: 3.13
Classifier: Programming Language :: Python :: 3.14
Classifier: Topic :: Security
Requires-Dist: ansible-core (>=2.15.13,<3.0.0)
Requires-Dist: ansible-runner (>=2.3.2,<3.0.0)
Requires-Dist: beautifulsoup4 (>=4.12.2,<5.0.0)
Requires-Dist: cachetools (>=5.3.2,<7.0.0)
Requires-Dist: cloudcheck (>=9.2.0,<10.0.0)
Requires-Dist: deepdiff (>=8.0.0,<9.0.0)
Requires-Dist: dnspython (>=2.7.0,<2.8.0)
Requires-Dist: httpx (>=0.28.1,<0.29.0)
Requires-Dist: idna (>=3.4,<4.0)
Requires-Dist: jinja2 (>=3.1.3,<4.0.0)
Requires-Dist: lxml (>=4.9.2,<7.0.0)
Requires-Dist: mmh3 (>=4.1,<6.0)
Requires-Dist: omegaconf (>=2.3.0,<3.0.0)
Requires-Dist: orjson (>=3.10.12,<4.0.0)
Requires-Dist: psutil (>=5.9.4,<8.0.0)
Requires-Dist: puremagic (>=1.28,<2.0)
Requires-Dist: pycryptodome (>=3.17,<4.0)
Requires-Dist: pydantic (>=2.9.2,<3.0.0)
Requires-Dist: pyjwt (>=2.7.0,<3.0.0)
Requires-Dist: pyzmq (>=26.0.3,<28.0.0)
Requires-Dist: radixtarget (>=3.0.13,<4.0.0)
Requires-Dist: regex (>=2024.4.16,<2027.0.0)
Requires-Dist: setproctitle (>=1.3.3,<2.0.0)
Requires-Dist: socksio (>=1.0.0,<2.0.0)
Requires-Dist: tabulate (==0.8.10)
Requires-Dist: tldextract (>=5.3.0,<6.0.0)
Requires-Dist: unidecode (>=1.3.8,<2.0.0)
Requires-Dist: websockets (>=14.0.0,<16.0.0)
Requires-Dist: wordninja (>=2.0.0,<3.0.0)
Requires-Dist: xmltojson (>=2.0.2,<3.0.0)
Requires-Dist: xxhash (>=3.5.0,<4.0.0)
Requires-Dist: yara-python (>=4.5.1,<5.0.0)
Project-URL: Documentation, https://www.blacklanternsecurity.com/bbot/
Project-URL: Discord, https://discord.com/invite/PZqkgxu5SA
Project-URL: Docker Hub, https://hub.docker.com/r/blacklanternsecurity/bbot
Project-URL: Homepage, https://github.com/blacklanternsecurity/bbot
Project-URL: Repository, https://github.com/blacklanternsecurity/bbot
